crawzy/__init__.py
crawzy/main.py
crawzy-0.1.dist-info/METADATA
crawzy-0.1.dist-info/WHEEL
crawzy-0.1.dist-info/entry_points.txt
crawzy-0.1.dist-info/licenses/LICENSE
crawzy-0.1.dist-info/RECORD
